lookaside/__init__.py
lookaside/cli.py
lookaside/lookaside.py
lookaside/util.py
lookaside-0.0.1.dist-info/METADATA
lookaside-0.0.1.dist-info/WHEEL
lookaside-0.0.1.dist-info/entry_points.txt
lookaside-0.0.1.dist-info/top_level.txt
lookaside-0.0.1.dist-info/RECORD
